{
    "cycles_program_begin": 2935342664826196,
    "cpu_cycles_pass2_start": 2935347924642432,
    "perf": [
        [
            0.30042600631713867,
            0.065198999999999993,
            0.043131000000000003,
            228660,
            229308,
            1585711006.8643179,
            2935343136543436,
            "doParsingAndDesignResolution",
            "entry"
        ],
        [
            0.52096199989318848,
            0.14240900000000001,
            0.051508999999999999,
            234380,
            235028,
            1585711007.0848539,
            2935343620566932,
            "doParsingAndDesignResolution",
            "exit"
        ],
        [
            0.59061217308044434,
            0.14727199999999999,
            0.053461000000000002,
            234380,
            235028,
            1585711007.1545041,
            2935343773453756,
            "doPostDesignResolutionToVir2Vcs",
            "entry"
        ],
        [
            0.81107020378112793,
            0.228323,
            0.063646999999999995,
            238992,
            238996,
            1585711007.3749621,
            2935344257283548,
            "doUptoVir2VcsNoSepCleanup",
            "entry"
        ],
        [
            1.9984750747680664,
            0.47207100000000002,
            0.093198000000000003,
            249228,
            249248,
            1585711008.562367,
            2935346863461958,
            "doUptoVir2VcsNoSepCleanup",
            "exit"
        ],
        [
            1.9986300468444824,
            0.47220200000000001,
            0.093224000000000001,
            249228,
            249248,
            1585711008.5625219,
            2935346863724820,
            "doRadify_vir2vcsAll",
            "entry"
        ],
        [
            2.1106421947479248,
            0.49237399999999998,
            0.098676,
            249228,
            249248,
            1585711008.6745341,
            2935347109649166,
            "doRadify_vir2vcsAll",
            "exit"
        ],
        [
            2.1107320785522461,
            0.49245,
            0.098691000000000001,
            249228,
            249248,
            1585711008.674624,
            2935347109768688,
            "doPostDesignResolutionToVir2Vcs",
            "exit"
        ],
        [
            2.1107821464538574,
            0.49249199999999999,
            0.098698999999999995,
            249228,
            249248,
            1585711008.674674,
            2935347109880470,
            "doGAToPass2",
            "entry"
        ],
        [
            2.4819440841674805,
            0.49495699999999998,
            0.10505200000000001,
            247412,
            249248,
            1585711009.045836,
            2935347924598196,
            "DoPass2",
            "entry"
        ],
        [
            3.2190780639648438,
            0.71154700000000004,
            0.13969599999999999,
            249388,
            249416,
            1585711009.78297,
            2935349542480184,
            "DoPass2",
            "exit"
        ]
    ],
    "MlibObjs": {},
    "LVLData": [
        "SIM"
    ],
    "CompileStrategy": "fullobj",
    "Misc": {
        "vcs_version": "N-2017.12-SP2-1_Full64",
        "vcs_build_date": "Build Date = Jul 14 2018 20:29:59",
        "master_pid": 13814,
        "VCS_HOME": "/usr/caen/vcs-2017.12-SP2-1",
        "daidir": "/afs/umich.edu/user/s/u/sunsusan/Desktop/group7w20/simv.daidir",
        "cwd": "/afs/umich.edu/user/s/u/sunsusan/Desktop/group7w20",
        "archive_dir": "archive.5",
        "csrc_abs": "/afs/umich.edu/user/s/u/sunsusan/Desktop/group7w20/csrc",
        "csrc": "csrc",
        "daidir_abs": "/afs/umich.edu/user/s/u/sunsusan/Desktop/group7w20/simv.daidir",
        "default_output_dir": "csrc"
    },
    "PrevCompiledModules": {
        "std": {
            "reYIK_d": {
                "archive": "archive.5/_prev_archive_1.a",
                "bytes": 33820,
                "mod": "std",
                "mode": 4,
                "checksum": 0,
                "out": "reYIK_d.o"
            }
        },
        "_vcs_unit__1327612396": {
            "jqQHP_d": {
                "archive": "archive.5/_prev_archive_1.a",
                "bytes": 30158,
                "mod": "_vcs_unit__1327612396",
                "mode": 4,
                "checksum": 0,
                "out": "jqQHP_d.o"
            }
        },
        "RS_0000": {
            "vG3v3_d": {
                "archive": "archive.5/_prev_archive_1.a",
                "bytes": 84846,
                "mod": "RS_0000",
                "mode": 4,
                "checksum": 0,
                "out": "vG3v3_d.o"
            }
        },
        "rob": {
            "vtxDx_d": {
                "archive": "archive.5/_prev_archive_1.a",
                "bytes": 57774,
                "mod": "rob",
                "mode": 4,
                "checksum": 0,
                "out": "vtxDx_d.o"
            }
        },
        "wand_sel_0001": {
            "ci1CE_d": {
                "archive": "archive.5/_prev_archive_1.a",
                "bytes": 61660,
                "mod": "wand_sel_0001",
                "mode": 4,
                "checksum": 0,
                "out": "ci1CE_d.o"
            }
        },
        "mem": {
            "FSbWZ_d": {
                "archive": "archive.5/_prev_archive_1.a",
                "bytes": 21144,
                "mod": "mem",
                "mode": 4,
                "checksum": 0,
                "out": "FSbWZ_d.o"
            }
        },
        "wand_sel_0000": {
            "hckDL_d": {
                "archive": "archive.5/_prev_archive_1.a",
                "bytes": 241864,
                "mod": "wand_sel_0000",
                "mode": 4,
                "checksum": 0,
                "out": "hckDL_d.o"
            }
        },
        "...MASTER...": {
            "amcQw_d": {
                "bytes": 7866,
                "mod": "...MASTER...",
                "mode": 4,
                "checksum": 0,
                "out": "objs/amcQw_d.o"
            }
        },
        "mult_stage": {
            "aUVMg_d": {
                "archive": "archive.5/_prev_archive_1.a",
                "bytes": 17522,
                "mod": "mult_stage",
                "mode": 4,
                "checksum": 0,
                "out": "aUVMg_d.o"
            }
        },
        "ex_stage_0000": {
            "tmdK7_d": {
                "archive": "archive.5/_prev_archive_1.a",
                "bytes": 35918,
                "mod": "ex_stage_0000",
                "mode": 4,
                "checksum": 0,
                "out": "tmdK7_d.o"
            }
        },
        "rs_psel_gen_0000": {
            "xjVMK_d": {
                "archive": "archive.5/_prev_archive_1.a",
                "bytes": 40204,
                "mod": "rs_psel_gen_0000",
                "mode": 4,
                "checksum": 0,
                "out": "xjVMK_d.o"
            }
        },
        "RS_Line_0000": {
            "Z4jCT_d": {
                "archive": "archive.5/_prev_archive_1.a",
                "bytes": 29622,
                "mod": "RS_Line_0000",
                "mode": 4,
                "checksum": 0,
                "out": "Z4jCT_d.o"
            }
        },
        "alu": {
            "C26kq_d": {
                "archive": "archive.5/_prev_archive_1.a",
                "bytes": 42556,
                "mod": "alu",
                "mode": 4,
                "checksum": 0,
                "out": "C26kq_d.o"
            }
        },
        "testbench": {
            "iAVhC_d": {
                "archive": "archive.5/_13814_archive_1.a",
                "bytes": 60466,
                "mod": "testbench",
                "out": "iAVhC_d.o",
                "mode": 4,
                "checksum": 0
            }
        },
        "decoder": {
            "zf0bY_d": {
                "archive": "archive.5/_prev_archive_1.a",
                "bytes": 22328,
                "mod": "decoder",
                "mode": 4,
                "checksum": 0,
                "out": "zf0bY_d.o"
            }
        },
        "brcond": {
            "VqGv5_d": {
                "archive": "archive.5/_prev_archive_1.a",
                "bytes": 10576,
                "mod": "brcond",
                "mode": 4,
                "checksum": 0,
                "out": "VqGv5_d.o"
            }
        },
        "processor_0000": {
            "UzNI6_d": {
                "archive": "archive.5/_prev_archive_1.a",
                "bytes": 374730,
                "mod": "processor_0000",
                "mode": 4,
                "checksum": 0,
                "out": "UzNI6_d.o"
            }
        }
    },
    "PEModules": [],
    "NameTable": {
        "std": [
            "std",
            "reYIK",
            "module",
            2
        ],
        "rob": [
            "rob",
            "vtxDx",
            "module",
            11
        ],
        "wand_sel_0001": [
            "wand_sel_0001",
            "ci1CE",
            "module",
            16
        ],
        "_vcs_unit__1327612396": [
            "_vcs_unit__1327612396",
            "jqQHP",
            "module",
            1
        ],
        "RS_0000": [
            "RS_0000",
            "vG3v3",
            "module",
            13
        ],
        "wand_sel_0000": [
            "wand_sel_0000",
            "hckDL",
            "module",
            15
        ],
        "mem": [
            "mem",
            "FSbWZ",
            "module",
            3
        ],
        "alu": [
            "alu",
            "C26kq",
            "module",
            5
        ],
        "testbench": [
            "testbench",
            "iAVhC",
            "module",
            4
        ],
        "brcond": [
            "brcond",
            "VqGv5",
            "module",
            6
        ],
        "decoder": [
            "decoder",
            "zf0bY",
            "module",
            8
        ],
        "ex_stage_0000": [
            "ex_stage_0000",
            "tmdK7",
            "module",
            7
        ],
        "mult_stage": [
            "mult_stage",
            "aUVMg",
            "module",
            9
        ],
        "processor_0000": [
            "processor_0000",
            "UzNI6",
            "module",
            10
        ],
        "RS_Line_0000": [
            "RS_Line_0000",
            "Z4jCT",
            "module",
            12
        ],
        "rs_psel_gen_0000": [
            "rs_psel_gen_0000",
            "xjVMK",
            "module",
            14
        ],
        "...MASTER...": [
            "SIM",
            "amcQw",
            "module",
            17
        ]
    },
    "stat": {
        "ru_self_cgstart": {
            "ru_nivcsw": 43,
            "ru_utime_sec": 0.49508600000000003,
            "ru_minflt": 28530,
            "ru_stime_sec": 0.10507900000000001,
            "ru_maxrss_kb": 78652,
            "ru_majflt": 0,
            "ru_nvcsw": 291
        },
        "CodeGen(%)": 29.818635149885264,
        "ru_childs_cgstart": {
            "ru_nivcsw": 7,
            "ru_utime_sec": 0.020580000000000001,
            "ru_minflt": 6350,
            "ru_stime_sec": 0.023344,
            "ru_maxrss_kb": 26484,
            "ru_majflt": 0,
            "ru_nvcsw": 18
        },
        "cpu_cycles_cgstart": 2935347924779618,
        "quadSpeed": 138925.40256325997,
        "nMops": 103212,
        "ru_childs_end": {
            "ru_nivcsw": 9,
            "ru_utime_sec": 0.022936999999999999,
            "ru_minflt": 6946,
            "ru_stime_sec": 0.026879,
            "ru_maxrss_kb": 26912,
            "ru_majflt": 0,
            "ru_nvcsw": 20
        },
        "nQuads": 30438,
        "realTime": 3.313601016998291,
        "outputSizePerQuad": 5.837965700768776,
        "ru_self_end": {
            "ru_nivcsw": 53,
            "ru_utime_sec": 0.71182500000000004,
            "ru_minflt": 34223,
            "ru_stime_sec": 0.15138799999999999,
            "ru_maxrss_kb": 89908,
            "ru_majflt": 0,
            "ru_nvcsw": 387
        },
        "totalObjSize": 177696,
        "Frontend(%)": 70.181364850114733,
        "cpu_cycles_end": 2935349749612124,
        "mopSpeed": 471081.16989812691,
        "cpu_cycles_total": 7084785928,
        "mop/quad": 3.3908929627439384,
        "peak_mem_kb": 249416
    },
    "CompileProcesses": [
        "cgproc.13814.json"
    ],
    "CurCompileUdps": {},
    "SIMBData": {
        "out": "amcQwB.o",
        "archive": "archive.5/_13814_archive_1.a",
        "bytes": 117132,
        "text": 0
    },
    "incremental": "on",
    "CurCompileModules": [
        "...MASTER...",
        "_vcs_unit__1327612396",
        "std",
        "mem",
        "testbench",
        "testbench",
        "alu",
        "brcond",
        "ex_stage_0000",
        "decoder",
        "mult_stage",
        "processor_0000",
        "rob",
        "RS_Line_0000",
        "RS_0000",
        "rs_psel_gen_0000",
        "wand_sel_0000",
        "wand_sel_0001"
    ],
    "rlimit": {
        "data": -1,
        "stack": -1
    },
    "CompileStatus": "Successful"
}